{"mean":{"confidence_interval":{"confidence_level":0.95,"lower_bound":3078685.948647058,"upper_bound":3089259.6441470585},"point_estimate":3083904.846470588,"standard_error":2697.2144679081716},"median":{"confidence_interval":{"confidence_level":0.95,"lower_bound":3074679.970588235,"upper_bound":3090100.117647059},"point_estimate":3080489.970588235,"standard_error":4190.207613828081},"median_abs_dev":{"confidence_interval":{"confidence_level":0.95,"lower_bound":20673.897303552378,"upper_bound":33982.8484202139},"point_estimate":27251.277663252196,"standard_error":3377.0314098254016},"slope":null,"std_dev":{"confidence_interval":{"confidence_level":0.95,"lower_bound":22895.040950675604,"upper_bound":30949.773595531835},"point_estimate":27059.988025887917,"standard_error":2061.2046100099733}}